.gitignore
MANIFEST.in
README.md
setup.py
HieraPy.egg-info/PKG-INFO
HieraPy.egg-info/SOURCES.txt
HieraPy.egg-info/dependency_links.txt
HieraPy.egg-info/requires.txt
HieraPy.egg-info/top_level.txt
hierapy/__init__.py
tests/test_hiera_config.py