Metadata-Version: 1.0
Name: HieraPy
Version: 0.0.3
Summary: Shy implementation of Puppet's Hiera configuration tool.
Home-page: https://github.com/ivannpaz/HieraPy
Author: Ivan N. (based on previous work by Alec Elton)
Author-email: ivannpaz@gmail.com
License: UNKNOWN
Platform: UNKNOWN
